{
    "wallpaper": "/home/larin/wallpaper/wallpaper.png",
    "alpha": "100",

    "special": {
        "background": "#1b1b13",
        "foreground": "#d6d4d9",
        "cursor": "#d6d4d9"
    },
    "colors": {
        "color0": "#1b1b13",
        "color1": "#7EA130",
        "color2": "#76884B",
        "color3": "#8FA44A",
        "color4": "#61718F",
        "color5": "#8C839E",
        "color6": "#9F9D9D",
        "color7": "#d6d4d9",
        "color8": "#959497",
        "color9": "#7EA130",
        "color10": "#76884B",
        "color11": "#8FA44A",
        "color12": "#61718F",
        "color13": "#8C839E",
        "color14": "#9F9D9D",
        "color15": "#d6d4d9"
    }
}
